cli_onprem/__init__.py
cli_onprem/__main__.py
cli_onprem/commands/__init__.py
cli_onprem/commands/docker_tar.py
cli_onprem/commands/helm_local.py
cli_onprem/commands/s3_share.py
cli_onprem/commands/tar_fat32.py
cli_onprem/core/__init__.py
cli_onprem/core/errors.py
cli_onprem/core/logging.py
cli_onprem/core/types.py
cli_onprem/services/__init__.py
cli_onprem/services/archive.py
cli_onprem/services/credential.py
cli_onprem/services/docker.py
cli_onprem/services/helm.py
cli_onprem/services/s3.py
cli_onprem/utils/__init__.py
cli_onprem/utils/file.py
cli_onprem/utils/formatting.py
cli_onprem/utils/fs.py
cli_onprem/utils/hash.py
cli_onprem/utils/shell.py
cli_onprem-2.2.2.dist-info/METADATA
cli_onprem-2.2.2.dist-info/WHEEL
cli_onprem-2.2.2.dist-info/entry_points.txt
cli_onprem-2.2.2.dist-info/licenses/LICENSE
cli_onprem-2.2.2.dist-info/RECORD
