Metadata-Version: 2.4
Name: cli-onprem
Version: 2.2.2
Summary: CLI tool for infrastructure engineers
Author-email: kang hee yong <cagojeiger89@gmail.com>
License: MIT License
License-File: LICENSE
Classifier: License :: OSI Approved :: MIT License
Classifier: Operating System :: OS Independent
Classifier: Programming Language :: Python :: 3
Classifier: Programming Language :: Python :: 3.9
Classifier: Programming Language :: Python :: 3.10
Classifier: Programming Language :: Python :: 3.11
Classifier: Programming Language :: Python :: 3.12
Classifier: Programming Language :: Python :: 3.13
Requires-Python: >=3.9
Requires-Dist: boto3>=1.28.0
Requires-Dist: pyyaml>=6.0.0
Requires-Dist: rich>=13.0.0
Requires-Dist: tqdm>=4.65.0
Requires-Dist: typer>=0.9.0
Requires-Dist: types-tqdm>=4.65.0
Provides-Extra: dev
Requires-Dist: black; extra == 'dev'
Requires-Dist: build; extra == 'dev'
Requires-Dist: mypy; extra == 'dev'
Requires-Dist: pre-commit; extra == 'dev'
Requires-Dist: pre-commit-uv; extra == 'dev'
Requires-Dist: pytest; extra == 'dev'
Requires-Dist: pytest-cov; extra == 'dev'
Requires-Dist: pytest-mypy-plugins; extra == 'dev'
Requires-Dist: python-semantic-release; extra == 'dev'
Requires-Dist: pyupgrade; extra == 'dev'
Requires-Dist: ruff; extra == 'dev'
Requires-Dist: twine; extra == 'dev'
Requires-Dist: types-pyyaml; extra == 'dev'
